example_pouyatlp/__init__.py
example_pouyatlp/example.py
HDL.v2-0.0.1.dist-info/LICENSE.txt
HDL.v2-0.0.1.dist-info/METADATA
HDL.v2-0.0.1.dist-info/WHEEL
HDL.v2-0.0.1.dist-info/top_level.txt
HDL.v2-0.0.1.dist-info/RECORD
