Metadata-Version: 2.1
Name: HDL.v2
Version: 0.0.1
Summary: Read the latest Real Python tutorials
Author: Pouyatlp
Author-email: Pouyatlp <useracctp@gmail.com>
License: MIT License
Project-URL: Homepage, https://github.com/Pouyatlp/Hand-Detection-Lib/tree/main
Classifier: License :: OSI Approved :: MIT License
Classifier: Programming Language :: Python
Classifier: Programming Language :: Python :: 3
Requires-Python: >=3.9
License-File: LICENSE.txt
